zxpath.py
zxpath-1.0.3.dist-info/METADATA
zxpath-1.0.3.dist-info/RECORD
zxpath-1.0.3.dist-info/WHEEL
zxpath-1.0.3.dist-info/top_level.txt
